{"municipalityCode":"234451","municipalityName":"南知多町","municipalityNameKana":null,"prefectureCode":"23","prefectureName":"愛知県","businesses":[{"businessKey":"17-6-000","businessName":"下水道事業（一） 事業コード6","businessType":"下水道事業（一） 事業コード6","estatBusinessCategory":"17/6/000","accountingType":"legal_applied","financialStory":{"year":"令和6年度","accountingType":"legal_applied","income":{"totalRevenue":124849,"totalExpense":130397,"operatingRevenue":27441,"nonOperatingRevenue":97408,"extraordinaryProfit":0,"operatingExpense":126391,"nonOperatingExpense":4005,"extraordinaryLoss":1,"netIncome":-5548,"revenueBreakdown":[{"id":"sewer-fee","label":"下水道使用料","value":27429,"group":"operating","note":"使用者が支払う料金"},{"id":"rainwater-burden","label":"雨水処理負担金","value":0,"group":"operating","note":"公費で負担する雨水処理分"},{"id":"other-operating-revenue","label":"その他営業収益","value":12,"group":"operating"},{"id":"national-subsidy","label":"国庫補助金","value":0,"group":"non-operating"},{"id":"prefectural-subsidy","label":"都道府県補助金","value":0,"group":"non-operating"},{"id":"other-account-subsidy","label":"他会計補助金（営業外収益）","value":39737,"group":"non-operating","note":"損益計算書上の科目。繰出基準内の補助も含むため、基準外繰入金とは一致しません"},{"id":"deferred-revenue-return","label":"長期前受金戻入","value":57664,"group":"non-operating","note":"過去の補助金等を減価償却に合わせて収益化した額"},{"id":"capital-cost-transfer","label":"資本費繰入収益","value":0,"group":"non-operating"},{"id":"miscellaneous-revenue","label":"雑収益","value":7,"group":"non-operating"},{"id":"extraordinary-profit-detail","label":"特別利益","value":0,"group":"extraordinary"}],"expenseBreakdown":[{"id":"pipeline","label":"管渠費","value":4978,"group":"operating"},{"id":"pump-station","label":"ポンプ場費","value":0,"group":"operating"},{"id":"treatment-plant","label":"処理場費","value":28700,"group":"operating"},{"id":"outsourced-construction","label":"受託工事費","value":0,"group":"operating"},{"id":"business","label":"業務費","value":0,"group":"operating"},{"id":"administration","label":"総係費","value":18635,"group":"operating"},{"id":"depreciation","label":"減価償却費","value":72044,"group":"operating","note":"施設の価値を使用年数に配分した費用"},{"id":"asset-retirement","label":"資産減耗費","value":2032,"group":"operating"},{"id":"regional-sewerage","label":"流域下水道管理運営費","value":0,"group":"operating"},{"id":"other-operating-expense","label":"その他営業費用","value":2,"group":"operating"},{"id":"interest","label":"支払利息","value":3272,"group":"non-operating"},{"id":"other-non-operating-expense","label":"その他営業外費用","value":733,"group":"non-operating"},{"id":"extraordinary-loss-detail","label":"特別損失","value":1,"group":"extraordinary"}]},"balance":{"fixedAssets":1315386,"currentAssets":46825,"deferredAssets":0,"totalAssets":1362211,"fixedLiabilities":198369,"currentLiabilities":52856,"deferredRevenue":896191,"totalLiabilities":1147416,"capital":78442,"surplus":136353,"capitalSurplus":134652,"retainedEarnings":1701,"otherSecuritiesValuationDifference":0,"totalNetAssets":214795,"priorNetAssets":209515,"priorCapital":67614,"priorSurplus":141901,"priorCapitalSurplus":134652,"priorRetainedEarnings":7249,"priorOtherSecuritiesValuationDifference":0},"status":{"state":"ready","label":"必要項目取得済み","message":"金額は地方公営企業決算状況調査の原表値（千円）から構成しています。"},"trace":[{"id":"24-2024-20","label":"令和6年度 地方財政状況調査","table":"第20表 損益計算書","sourceUrl":"https://www.e-stat.go.jp/stat-search/file-download?&statInfId=000040327226&fileKind=0"},{"id":"25-2024-21","label":"令和6年度 地方財政状況調査","table":"第21表 費用構成表","sourceUrl":"https://www.e-stat.go.jp/stat-search/file-download?&statInfId=000040327228&fileKind=0"},{"id":"26-2024-22","label":"令和6年度 地方財政状況調査","table":"第22表 貸借対照表","sourceUrl":"https://www.e-stat.go.jp/stat-search/file-download?&statInfId=000040327230&fileKind=0"},{"id":"5-2023-22","label":"令和5年度 地方財政状況調査","table":"第22表 貸借対照表","sourceUrl":"https://www.e-stat.go.jp/stat-search/file-download?&statInfId=000040328395&fileKind=0","note":"前年度末の純資産と内訳の比較に使用"}]},"financialStatementsReady":true,"evidenceEntries":[["householdFee20m3Yen",{"value":2700,"unit":"yen_per_month_tax_included","tableNo":33,"tableName":"一般家庭用20m³／月使用料","sourceUrl":"https://www.e-stat.go.jp/stat-search/file-download?&statInfId=000040327245&fileKind=0"}],["sewerFeeRevenue",{"value":27429,"unit":"thousand_yen","tableNo":20,"tableName":"下水道使用料収入","sourceUrl":"https://www.e-stat.go.jp/stat-search/file-download?&statInfId=000040327226&fileKind=0"}],["annualBillableVolume",{"value":202111,"unit":"cubic_meter","tableNo":10,"tableName":"年間有収水量","sourceUrl":"https://www.e-stat.go.jp/stat-search/file-download?&statInfId=000040327218&fileKind=0"}],["wastewaterTreatmentCost",{"value":52313,"unit":"thousand_yen","tableNo":32,"tableName":"汚水処理費（合計）","sourceUrl":"https://www.e-stat.go.jp/stat-search/file-download?&statInfId=000040327244&fileKind=0"}],["opexComponent",{"value":52313,"unit":"thousand_yen","tableNo":32,"tableName":"汚水処理費（維持管理費分）","sourceUrl":"https://www.e-stat.go.jp/stat-search/file-download?&statInfId=000040327244&fileKind=0"}],["capitalCostComponent",{"value":0,"unit":"thousand_yen","tableNo":32,"tableName":"汚水処理費（資本費分）","sourceUrl":"https://www.e-stat.go.jp/stat-search/file-download?&statInfId=000040327244&fileKind=0"}],["ordinaryProfitLoss",{"value":-5547,"unit":"thousand_yen","tableNo":20,"tableName":"経常損益","sourceUrl":"https://www.e-stat.go.jp/stat-search/file-download?&statInfId=000040327226&fileKind=0"}],["netIncome",{"value":-5548,"unit":"thousand_yen","tableNo":20,"tableName":"当年度純損益","sourceUrl":"https://www.e-stat.go.jp/stat-search/file-download?&statInfId=000040327226&fileKind=0"}],["generalAccountTransfer",{"value":39737,"unit":"thousand_yen","tableNo":40,"tableName":"他会計繰入金","sourceUrl":"https://www.e-stat.go.jp/stat-search/file-download?&statInfId=000040327247&fileKind=0"}],["nonStandardTransfer",{"value":31694,"unit":"thousand_yen","tableNo":40,"tableName":"基準外繰入合計","sourceUrl":"https://www.e-stat.go.jp/stat-search/file-download?&statInfId=000040327247&fileKind=0"}],["table40RainwaterBurden",{"value":0,"unit":"thousand_yen","tableNo":40,"tableName":"雨水処理負担金（実繰入額）","sourceUrl":"https://www.e-stat.go.jp/stat-search/file-download?&statInfId=000040327247&fileKind=0"}],["table40OtherAccountSubsidy",{"value":39737,"unit":"thousand_yen","tableNo":40,"tableName":"他会計補助金（実繰入額）","sourceUrl":"https://www.e-stat.go.jp/stat-search/file-download?&statInfId=000040327247&fileKind=0"}],["table40CapitalOtherAccountSubsidy",{"value":144,"unit":"thousand_yen","tableNo":40,"tableName":"資本勘定の他会計補助金（実繰入額）","sourceUrl":"https://www.e-stat.go.jp/stat-search/file-download?&statInfId=000040327247&fileKind=0"}],["table40RainwaterBurdenNonStandard",{"value":0,"unit":"thousand_yen","tableNo":40,"tableName":"雨水処理負担金（基準外）","sourceUrl":"https://www.e-stat.go.jp/stat-search/file-download?&statInfId=000040327247&fileKind=0"}]],"annualFinancials":[{"surveyYear":2023,"fiscalYearLabel":"令和5年度","accountingType":"legal_applied","sewerFeeRevenue":27600,"householdFee20m3Yen":2700,"annualBillableVolume":205949,"wastewaterTreatmentCost":46137,"opexComponent":46137,"capitalCostComponent":0,"operatingRevenue":27613,"operatingExpense":123973,"ordinaryRevenue":null,"ordinaryExpense":null,"ordinaryProfitLoss":7246,"netIncome":7249,"accumulatedDeficit":null,"totalRevenueNonLegal":null,"totalExpenseNonLegal":null,"realBalance":null,"revenueExpenditureRatio":null,"standardTransfer":null,"nonStandardTransfer":51344,"bondBalance":233893,"bondIssued":null,"bondRedemption":null,"servicePopulation":1672,"connectedPopulation":1630,"treatedVolume":257643,"dataQualityStatus":"ok","flagsJson":"[]","diagnosisResult":{"surveyYear":2023,"feeUnitPriceYenPerM3":134.0138,"treatmentCostYenPerM3":224.0215,"expenseRecoveryRate":59.8218,"requiredRevisionRateTo80":0.337305,"requiredRevisionRateTo100":0.671631,"requiredRevisionRateTo150yen":0.119288,"accountingBalanceLabel":"経常損益は判定不可 / 純利益","feeAdequacyLabel":"重点監視","revisionRiskScore":85,"revisionRiskLabel":"参考スコア80以上","diagnosisComment":"最新決算の経費回収率は59.8%であり、汚水処理費に対する使用料収入の不足割合が大きい状態です。費用や有収水量が変わらない仮定では、経費回収率100%相当の使用料収入は約67.2%の増加となる単純試算です。実際の使用料改定は、審議会、条例改正、一般会計繰入、投資計画等を踏まえて決まります。"}},{"surveyYear":2024,"fiscalYearLabel":"令和6年度","accountingType":"legal_applied","sewerFeeRevenue":27429,"householdFee20m3Yen":2700,"annualBillableVolume":202111,"wastewaterTreatmentCost":52313,"opexComponent":52313,"capitalCostComponent":0,"operatingRevenue":27441,"operatingExpense":126391,"ordinaryRevenue":null,"ordinaryExpense":null,"ordinaryProfitLoss":-5547,"netIncome":-5548,"accumulatedDeficit":null,"totalRevenueNonLegal":null,"totalExpenseNonLegal":null,"realBalance":null,"revenueExpenditureRatio":null,"standardTransfer":null,"nonStandardTransfer":31694,"bondBalance":229144,"bondIssued":null,"bondRedemption":null,"servicePopulation":1627,"connectedPopulation":1597,"treatedVolume":201299,"dataQualityStatus":"ok","flagsJson":"[]","table40RainwaterBurden":0,"table40OtherAccountSubsidy":39737,"table40CapitalOtherAccountSubsidy":144,"table40RainwaterBurdenNonStandard":0,"table40OtherAccountSubsidyNonStandard":20722,"table40CapitalOtherAccountSubsidyNonStandard":144,"diagnosisResult":{"surveyYear":2024,"feeUnitPriceYenPerM3":135.7126,"treatmentCostYenPerM3":258.833,"expenseRecoveryRate":52.4325,"requiredRevisionRateTo80":0.525771,"requiredRevisionRateTo100":0.907214,"requiredRevisionRateTo150yen":0.105277,"accountingBalanceLabel":"経常損益は判定不可 / 純損失","feeAdequacyLabel":"重点監視","revisionRiskScore":85,"revisionRiskLabel":"参考スコア80以上","diagnosisComment":"最新決算の経費回収率は52.4%であり、汚水処理費に対する使用料収入の不足割合が大きい状態です。費用や有収水量が変わらない仮定では、経費回収率100%相当の使用料収入は約90.7%の増加となる単純試算です。実際の使用料改定は、審議会、条例改正、一般会計繰入、投資計画等を踏まえて決まります。"}}]},{"businessKey":"17-6-000","businessName":"下水道事業（一） 事業コード6","businessType":"下水道事業（一） 事業コード6","estatBusinessCategory":"17/6/000","accountingType":"non_legal_applied","financialStory":{"year":"令和6年度","accountingType":"legal_applied","income":{"totalRevenue":124849,"totalExpense":130397,"operatingRevenue":27441,"nonOperatingRevenue":97408,"extraordinaryProfit":0,"operatingExpense":126391,"nonOperatingExpense":4005,"extraordinaryLoss":1,"netIncome":-5548,"revenueBreakdown":[{"id":"sewer-fee","label":"下水道使用料","value":27429,"group":"operating","note":"使用者が支払う料金"},{"id":"rainwater-burden","label":"雨水処理負担金","value":0,"group":"operating","note":"公費で負担する雨水処理分"},{"id":"other-operating-revenue","label":"その他営業収益","value":12,"group":"operating"},{"id":"national-subsidy","label":"国庫補助金","value":0,"group":"non-operating"},{"id":"prefectural-subsidy","label":"都道府県補助金","value":0,"group":"non-operating"},{"id":"other-account-subsidy","label":"他会計補助金（営業外収益）","value":39737,"group":"non-operating","note":"損益計算書上の科目。繰出基準内の補助も含むため、基準外繰入金とは一致しません"},{"id":"deferred-revenue-return","label":"長期前受金戻入","value":57664,"group":"non-operating","note":"過去の補助金等を減価償却に合わせて収益化した額"},{"id":"capital-cost-transfer","label":"資本費繰入収益","value":0,"group":"non-operating"},{"id":"miscellaneous-revenue","label":"雑収益","value":7,"group":"non-operating"},{"id":"extraordinary-profit-detail","label":"特別利益","value":0,"group":"extraordinary"}],"expenseBreakdown":[{"id":"pipeline","label":"管渠費","value":4978,"group":"operating"},{"id":"pump-station","label":"ポンプ場費","value":0,"group":"operating"},{"id":"treatment-plant","label":"処理場費","value":28700,"group":"operating"},{"id":"outsourced-construction","label":"受託工事費","value":0,"group":"operating"},{"id":"business","label":"業務費","value":0,"group":"operating"},{"id":"administration","label":"総係費","value":18635,"group":"operating"},{"id":"depreciation","label":"減価償却費","value":72044,"group":"operating","note":"施設の価値を使用年数に配分した費用"},{"id":"asset-retirement","label":"資産減耗費","value":2032,"group":"operating"},{"id":"regional-sewerage","label":"流域下水道管理運営費","value":0,"group":"operating"},{"id":"other-operating-expense","label":"その他営業費用","value":2,"group":"operating"},{"id":"interest","label":"支払利息","value":3272,"group":"non-operating"},{"id":"other-non-operating-expense","label":"その他営業外費用","value":733,"group":"non-operating"},{"id":"extraordinary-loss-detail","label":"特別損失","value":1,"group":"extraordinary"}]},"balance":{"fixedAssets":1315386,"currentAssets":46825,"deferredAssets":0,"totalAssets":1362211,"fixedLiabilities":198369,"currentLiabilities":52856,"deferredRevenue":896191,"totalLiabilities":1147416,"capital":78442,"surplus":136353,"capitalSurplus":134652,"retainedEarnings":1701,"otherSecuritiesValuationDifference":0,"totalNetAssets":214795,"priorNetAssets":209515,"priorCapital":67614,"priorSurplus":141901,"priorCapitalSurplus":134652,"priorRetainedEarnings":7249,"priorOtherSecuritiesValuationDifference":0},"status":{"state":"ready","label":"必要項目取得済み","message":"金額は地方公営企業決算状況調査の原表値（千円）から構成しています。"},"trace":[{"id":"24-2024-20","label":"令和6年度 地方財政状況調査","table":"第20表 損益計算書","sourceUrl":"https://www.e-stat.go.jp/stat-search/file-download?&statInfId=000040327226&fileKind=0"},{"id":"25-2024-21","label":"令和6年度 地方財政状況調査","table":"第21表 費用構成表","sourceUrl":"https://www.e-stat.go.jp/stat-search/file-download?&statInfId=000040327228&fileKind=0"},{"id":"26-2024-22","label":"令和6年度 地方財政状況調査","table":"第22表 貸借対照表","sourceUrl":"https://www.e-stat.go.jp/stat-search/file-download?&statInfId=000040327230&fileKind=0"},{"id":"5-2023-22","label":"令和5年度 地方財政状況調査","table":"第22表 貸借対照表","sourceUrl":"https://www.e-stat.go.jp/stat-search/file-download?&statInfId=000040328395&fileKind=0","note":"前年度末の純資産と内訳の比較に使用"}]},"financialStatementsReady":true,"evidenceEntries":[["householdFee20m3Yen",{"value":2562,"unit":"yen_per_month_tax_included","tableNo":33,"tableName":"一般家庭用20m³／月使用料","sourceUrl":"https://www.e-stat.go.jp/stat-search/file-download?&statInfId=000040107400&fileKind=0"}],["sewerFeeRevenue",{"value":24911,"unit":"thousand_yen","tableNo":26,"tableName":"下水道使用料収入","sourceUrl":"https://www.e-stat.go.jp/stat-search/file-download?&statInfId=000040107397&fileKind=0"}],["annualBillableVolume",{"value":210717,"unit":"cubic_meter","tableNo":10,"tableName":"年間有収水量","sourceUrl":"https://www.e-stat.go.jp/stat-search/file-download?&statInfId=000040107384&fileKind=0"}],["wastewaterTreatmentCost",{"value":31103,"unit":"thousand_yen","tableNo":32,"tableName":"汚水処理費（合計）","sourceUrl":"https://www.e-stat.go.jp/stat-search/file-download?&statInfId=000040107399&fileKind=0"}],["opexComponent",{"value":28844,"unit":"thousand_yen","tableNo":32,"tableName":"汚水処理費（維持管理費分）","sourceUrl":"https://www.e-stat.go.jp/stat-search/file-download?&statInfId=000040107399&fileKind=0"}],["capitalCostComponent",{"value":2259,"unit":"thousand_yen","tableNo":32,"tableName":"汚水処理費（資本費分）","sourceUrl":"https://www.e-stat.go.jp/stat-search/file-download?&statInfId=000040107399&fileKind=0"}],["totalRevenueNonLegal",{"value":53385,"unit":"thousand_yen","tableNo":26,"tableName":"総収益","sourceUrl":"https://www.e-stat.go.jp/stat-search/file-download?&statInfId=000040107397&fileKind=0"}],["totalExpenseNonLegal",{"value":32837,"unit":"thousand_yen","tableNo":26,"tableName":"総費用","sourceUrl":"https://www.e-stat.go.jp/stat-search/file-download?&statInfId=000040107397&fileKind=0"}],["generalAccountTransfer",{"value":32915,"unit":"thousand_yen","tableNo":40,"tableName":"他会計繰入金","sourceUrl":"https://www.e-stat.go.jp/stat-search/file-download?&statInfId=000040107402&fileKind=0"}],["nonStandardTransfer",{"value":0,"unit":"thousand_yen","tableNo":40,"tableName":"基準外繰入合計","sourceUrl":"https://www.e-stat.go.jp/stat-search/file-download?&statInfId=000040107402&fileKind=0"}],["bondBalance",{"value":245585,"unit":"thousand_yen","tableNo":24,"tableName":"地方債残高","sourceUrl":"https://www.e-stat.go.jp/stat-search/file-download?&statInfId=000040107395&fileKind=0"}],["servicePopulation",{"value":1712,"unit":"people","tableNo":10,"tableName":"現在処理区域内人口","sourceUrl":"https://www.e-stat.go.jp/stat-search/file-download?&statInfId=000040107384&fileKind=0"}],["connectedPopulation",{"value":1674,"unit":"people","tableNo":10,"tableName":"現在水洗便所設置済人口","sourceUrl":"https://www.e-stat.go.jp/stat-search/file-download?&statInfId=000040107384&fileKind=0"}],["treatedVolume",{"value":209277,"unit":"cubic_meter","tableNo":10,"tableName":"汚水処理水量","sourceUrl":"https://www.e-stat.go.jp/stat-search/file-download?&statInfId=000040107384&fileKind=0"}]],"annualFinancials":[{"surveyYear":2020,"fiscalYearLabel":"令和2年度","accountingType":"non_legal_applied","sewerFeeRevenue":30213,"householdFee20m3Yen":2562,"annualBillableVolume":213238,"wastewaterTreatmentCost":31986,"opexComponent":29376,"capitalCostComponent":2610,"operatingRevenue":null,"operatingExpense":null,"ordinaryRevenue":null,"ordinaryExpense":null,"ordinaryProfitLoss":null,"netIncome":null,"accumulatedDeficit":null,"totalRevenueNonLegal":59535,"totalExpenseNonLegal":34085,"realBalance":null,"revenueExpenditureRatio":174.6662754877512,"standardTransfer":null,"nonStandardTransfer":0,"bondBalance":253957,"bondIssued":null,"bondRedemption":null,"servicePopulation":1806,"connectedPopulation":1768,"treatedVolume":210894,"dataQualityStatus":"ok","flagsJson":"[]","generalAccountTransfer":30153,"diagnosisResult":{"surveyYear":2020,"feeUnitPriceYenPerM3":141.6868,"treatmentCostYenPerM3":150.0014,"expenseRecoveryRate":94.4569,"requiredRevisionRateTo80":-0.153053,"requiredRevisionRateTo100":0.058684,"requiredRevisionRateTo150yen":0.058673,"accountingBalanceLabel":"実質収支は判定不可 / 収益的収支は均衡以上","feeAdequacyLabel":"やや不足","revisionRiskScore":35,"revisionRiskLabel":"参考スコア30〜59","diagnosisComment":"最新決算の経費回収率は94.5%であり、下水道使用料収入が汚水処理費を下回っています。費用や有収水量が変わらない仮定では、経費回収率100%相当の使用料収入は約5.9%の増加となる単純試算です。"}},{"surveyYear":2021,"fiscalYearLabel":"令和3年度","accountingType":"non_legal_applied","sewerFeeRevenue":29841,"householdFee20m3Yen":2562,"annualBillableVolume":211691,"wastewaterTreatmentCost":32751,"opexComponent":32751,"capitalCostComponent":0,"operatingRevenue":null,"operatingExpense":null,"ordinaryRevenue":null,"ordinaryExpense":null,"ordinaryProfitLoss":null,"netIncome":null,"accumulatedDeficit":null,"totalRevenueNonLegal":61591,"totalExpenseNonLegal":37116,"realBalance":null,"revenueExpenditureRatio":165.9419118439487,"standardTransfer":null,"nonStandardTransfer":0,"bondBalance":247322,"bondIssued":null,"bondRedemption":null,"servicePopulation":1767,"connectedPopulation":1733,"treatedVolume":211062,"dataQualityStatus":"ok","flagsJson":"[]","generalAccountTransfer":29092,"diagnosisResult":{"surveyYear":2021,"feeUnitPriceYenPerM3":140.9649,"treatmentCostYenPerM3":154.7113,"expenseRecoveryRate":91.1148,"requiredRevisionRateTo80":-0.121987,"requiredRevisionRateTo100":0.097517,"requiredRevisionRateTo150yen":0.064095,"accountingBalanceLabel":"実質収支は判定不可 / 収益的収支は均衡以上","feeAdequacyLabel":"やや不足","revisionRiskScore":35,"revisionRiskLabel":"参考スコア30〜59","diagnosisComment":"最新決算の経費回収率は91.1%であり、下水道使用料収入が汚水処理費を下回っています。費用や有収水量が変わらない仮定では、経費回収率100%相当の使用料収入は約9.8%の増加となる単純試算です。"}},{"surveyYear":2022,"fiscalYearLabel":"令和4年度","accountingType":"non_legal_applied","sewerFeeRevenue":24911,"householdFee20m3Yen":2562,"annualBillableVolume":210717,"wastewaterTreatmentCost":31103,"opexComponent":28844,"capitalCostComponent":2259,"operatingRevenue":null,"operatingExpense":null,"ordinaryRevenue":null,"ordinaryExpense":null,"ordinaryProfitLoss":null,"netIncome":null,"accumulatedDeficit":null,"totalRevenueNonLegal":53385,"totalExpenseNonLegal":32837,"realBalance":null,"revenueExpenditureRatio":162.5757529615982,"standardTransfer":null,"nonStandardTransfer":0,"bondBalance":245585,"bondIssued":null,"bondRedemption":null,"servicePopulation":1712,"connectedPopulation":1674,"treatedVolume":209277,"dataQualityStatus":"ok","flagsJson":"[]","generalAccountTransfer":32915,"diagnosisResult":{"surveyYear":2022,"feeUnitPriceYenPerM3":118.2202,"treatmentCostYenPerM3":147.6056,"expenseRecoveryRate":80.092,"requiredRevisionRateTo80":-0.001149,"requiredRevisionRateTo100":0.248564,"requiredRevisionRateTo150yen":0.268819,"accountingBalanceLabel":"実質収支は判定不可 / 収益的収支は均衡以上","feeAdequacyLabel":"要注意","revisionRiskScore":35,"revisionRiskLabel":"参考スコア30〜59","diagnosisComment":"最新決算の経費回収率は80.1%であり、下水道使用料収入が汚水処理費を下回っています。費用や有収水量が変わらない仮定では、経費回収率100%相当の使用料収入は約24.9%の増加となる単純試算です。"}}]}],"revisionEvents":[],"servedServiceMemberships":[]}