{"municipalityCode":"293628","municipalityName":"三宅町","municipalityNameKana":null,"prefectureCode":"29","prefectureName":"奈良県","businesses":[{"businessKey":"17-1-000","businessName":"下水道事業（一） 事業コード1","businessType":"下水道事業（一） 事業コード1","estatBusinessCategory":"17/1/000","accountingType":"legal_applied","financialStory":{"year":"令和6年度","accountingType":"legal_applied","income":{"totalRevenue":211690,"totalExpense":203251,"operatingRevenue":48508,"nonOperatingRevenue":163175,"extraordinaryProfit":7,"operatingExpense":192668,"nonOperatingExpense":10576,"extraordinaryLoss":7,"netIncome":8439,"revenueBreakdown":[{"id":"sewer-fee","label":"下水道使用料","value":48357,"group":"operating","note":"使用者が支払う料金"},{"id":"rainwater-burden","label":"雨水処理負担金","value":0,"group":"operating","note":"公費で負担する雨水処理分"},{"id":"other-operating-revenue","label":"その他営業収益","value":151,"group":"operating"},{"id":"national-subsidy","label":"国庫補助金","value":5814,"group":"non-operating"},{"id":"prefectural-subsidy","label":"都道府県補助金","value":0,"group":"non-operating"},{"id":"other-account-subsidy","label":"他会計補助金（営業外収益）","value":83702,"group":"non-operating","note":"損益計算書上の科目。繰出基準内の補助も含むため、基準外繰入金とは一致しません"},{"id":"deferred-revenue-return","label":"長期前受金戻入","value":73623,"group":"non-operating","note":"過去の補助金等を減価償却に合わせて収益化した額"},{"id":"capital-cost-transfer","label":"資本費繰入収益","value":0,"group":"non-operating"},{"id":"miscellaneous-revenue","label":"雑収益","value":11,"group":"non-operating"},{"id":"extraordinary-profit-detail","label":"特別利益","value":7,"group":"extraordinary"}],"expenseBreakdown":[{"id":"pipeline","label":"管渠費","value":3360,"group":"operating"},{"id":"pump-station","label":"ポンプ場費","value":0,"group":"operating"},{"id":"treatment-plant","label":"処理場費","value":0,"group":"operating"},{"id":"outsourced-construction","label":"受託工事費","value":0,"group":"operating"},{"id":"business","label":"業務費","value":0,"group":"operating"},{"id":"administration","label":"総係費","value":25259,"group":"operating"},{"id":"depreciation","label":"減価償却費","value":141879,"group":"operating","note":"施設の価値を使用年数に配分した費用"},{"id":"asset-retirement","label":"資産減耗費","value":0,"group":"operating"},{"id":"regional-sewerage","label":"流域下水道管理運営費","value":22170,"group":"operating"},{"id":"other-operating-expense","label":"その他営業費用","value":0,"group":"operating"},{"id":"interest","label":"支払利息","value":8906,"group":"non-operating"},{"id":"other-non-operating-expense","label":"その他営業外費用","value":1670,"group":"non-operating"},{"id":"extraordinary-loss-detail","label":"特別損失","value":7,"group":"extraordinary"}]},"balance":{"fixedAssets":3055236,"currentAssets":37853,"deferredAssets":0,"totalAssets":3093089,"fixedLiabilities":745660,"currentLiabilities":115785,"deferredRevenue":1709513,"totalLiabilities":2570958,"capital":523138,"surplus":-1007,"capitalSurplus":0,"retainedEarnings":-1007,"otherSecuritiesValuationDifference":0,"totalNetAssets":522131,"priorNetAssets":513692,"priorCapital":523139,"priorSurplus":-9447,"priorCapitalSurplus":0,"priorRetainedEarnings":-9447,"priorOtherSecuritiesValuationDifference":0},"status":{"state":"ready","label":"必要項目取得済み","message":"金額は地方公営企業決算状況調査の原表値（千円）から構成しています。"},"trace":[{"id":"24-2024-20","label":"令和6年度 地方財政状況調査","table":"第20表 損益計算書","sourceUrl":"https://www.e-stat.go.jp/stat-search/file-download?&statInfId=000040327226&fileKind=0"},{"id":"25-2024-21","label":"令和6年度 地方財政状況調査","table":"第21表 費用構成表","sourceUrl":"https://www.e-stat.go.jp/stat-search/file-download?&statInfId=000040327228&fileKind=0"},{"id":"26-2024-22","label":"令和6年度 地方財政状況調査","table":"第22表 貸借対照表","sourceUrl":"https://www.e-stat.go.jp/stat-search/file-download?&statInfId=000040327230&fileKind=0"},{"id":"5-2023-22","label":"令和5年度 地方財政状況調査","table":"第22表 貸借対照表","sourceUrl":"https://www.e-stat.go.jp/stat-search/file-download?&statInfId=000040328395&fileKind=0","note":"前年度末の純資産と内訳の比較に使用"}]},"financialStatementsReady":true,"evidenceEntries":[["householdFee20m3Yen",{"value":2530,"unit":"yen_per_month_tax_included","tableNo":33,"tableName":"一般家庭用20m³／月使用料","sourceUrl":"https://www.e-stat.go.jp/stat-search/file-download?&statInfId=000040327245&fileKind=0"}],["sewerFeeRevenue",{"value":48357,"unit":"thousand_yen","tableNo":20,"tableName":"下水道使用料収入","sourceUrl":"https://www.e-stat.go.jp/stat-search/file-download?&statInfId=000040327226&fileKind=0"}],["annualBillableVolume",{"value":419719,"unit":"cubic_meter","tableNo":10,"tableName":"年間有収水量","sourceUrl":"https://www.e-stat.go.jp/stat-search/file-download?&statInfId=000040327218&fileKind=0"}],["wastewaterTreatmentCost",{"value":62951,"unit":"thousand_yen","tableNo":32,"tableName":"汚水処理費（合計）","sourceUrl":"https://www.e-stat.go.jp/stat-search/file-download?&statInfId=000040327244&fileKind=0"}],["opexComponent",{"value":51423,"unit":"thousand_yen","tableNo":32,"tableName":"汚水処理費（維持管理費分）","sourceUrl":"https://www.e-stat.go.jp/stat-search/file-download?&statInfId=000040327244&fileKind=0"}],["capitalCostComponent",{"value":11528,"unit":"thousand_yen","tableNo":32,"tableName":"汚水処理費（資本費分）","sourceUrl":"https://www.e-stat.go.jp/stat-search/file-download?&statInfId=000040327244&fileKind=0"}],["ordinaryProfitLoss",{"value":8439,"unit":"thousand_yen","tableNo":20,"tableName":"経常損益","sourceUrl":"https://www.e-stat.go.jp/stat-search/file-download?&statInfId=000040327226&fileKind=0"}],["netIncome",{"value":8439,"unit":"thousand_yen","tableNo":20,"tableName":"当年度純損益","sourceUrl":"https://www.e-stat.go.jp/stat-search/file-download?&statInfId=000040327226&fileKind=0"}],["generalAccountTransfer",{"value":83702,"unit":"thousand_yen","tableNo":40,"tableName":"他会計繰入金","sourceUrl":"https://www.e-stat.go.jp/stat-search/file-download?&statInfId=000040327247&fileKind=0"}],["nonStandardTransfer",{"value":53861,"unit":"thousand_yen","tableNo":40,"tableName":"基準外繰入合計","sourceUrl":"https://www.e-stat.go.jp/stat-search/file-download?&statInfId=000040327247&fileKind=0"}],["table40RainwaterBurden",{"value":0,"unit":"thousand_yen","tableNo":40,"tableName":"雨水処理負担金（実繰入額）","sourceUrl":"https://www.e-stat.go.jp/stat-search/file-download?&statInfId=000040327247&fileKind=0"}],["table40OtherAccountSubsidy",{"value":83702,"unit":"thousand_yen","tableNo":40,"tableName":"他会計補助金（実繰入額）","sourceUrl":"https://www.e-stat.go.jp/stat-search/file-download?&statInfId=000040327247&fileKind=0"}],["table40CapitalOtherAccountSubsidy",{"value":41373,"unit":"thousand_yen","tableNo":40,"tableName":"資本勘定の他会計補助金（実繰入額）","sourceUrl":"https://www.e-stat.go.jp/stat-search/file-download?&statInfId=000040327247&fileKind=0"}],["table40RainwaterBurdenNonStandard",{"value":0,"unit":"thousand_yen","tableNo":40,"tableName":"雨水処理負担金（基準外）","sourceUrl":"https://www.e-stat.go.jp/stat-search/file-download?&statInfId=000040327247&fileKind=0"}]],"annualFinancials":[{"surveyYear":2022,"fiscalYearLabel":"令和4年度","accountingType":"legal_applied","sewerFeeRevenue":45505,"householdFee20m3Yen":2530,"annualBillableVolume":395697,"wastewaterTreatmentCost":59355,"opexComponent":30732,"capitalCostComponent":28623,"operatingRevenue":45585,"operatingExpense":173933,"ordinaryRevenue":null,"ordinaryExpense":null,"ordinaryProfitLoss":-11573,"netIncome":-15762,"accumulatedDeficit":null,"totalRevenueNonLegal":null,"totalExpenseNonLegal":null,"realBalance":null,"revenueExpenditureRatio":null,"standardTransfer":null,"nonStandardTransfer":73199,"bondBalance":1063970,"bondIssued":null,"bondRedemption":null,"servicePopulation":4921,"connectedPopulation":4778,"treatedVolume":460113,"dataQualityStatus":"ok","flagsJson":"[]","diagnosisResult":{"surveyYear":2022,"feeUnitPriceYenPerM3":114.9996,"treatmentCostYenPerM3":150.0011,"expenseRecoveryRate":76.6658,"requiredRevisionRateTo80":0.04349,"requiredRevisionRateTo100":0.304363,"requiredRevisionRateTo150yen":0.304352,"accountingBalanceLabel":"経常損益は判定不可 / 純損失","feeAdequacyLabel":"重点監視","revisionRiskScore":85,"revisionRiskLabel":"参考スコア80以上","diagnosisComment":"最新決算の経費回収率は76.7%であり、汚水処理費に対する使用料収入の不足割合が大きい状態です。費用や有収水量が変わらない仮定では、経費回収率100%相当の使用料収入は約30.4%の増加となる単純試算です。実際の使用料改定は、審議会、条例改正、一般会計繰入、投資計画等を踏まえて決まります。"}},{"surveyYear":2023,"fiscalYearLabel":"令和5年度","accountingType":"legal_applied","sewerFeeRevenue":48487,"householdFee20m3Yen":2530,"annualBillableVolume":421304,"wastewaterTreatmentCost":63195,"opexComponent":33664,"capitalCostComponent":29531,"operatingRevenue":48565,"operatingExpense":176370,"ordinaryRevenue":null,"ordinaryExpense":null,"ordinaryProfitLoss":6314,"netIncome":6315,"accumulatedDeficit":null,"totalRevenueNonLegal":null,"totalExpenseNonLegal":null,"realBalance":null,"revenueExpenditureRatio":null,"standardTransfer":null,"nonStandardTransfer":64287,"bondBalance":947790,"bondIssued":null,"bondRedemption":null,"servicePopulation":4849,"connectedPopulation":4709,"treatedVolume":489888,"dataQualityStatus":"ok","flagsJson":"[]","diagnosisResult":{"surveyYear":2023,"feeUnitPriceYenPerM3":115.0879,"treatmentCostYenPerM3":149.9986,"expenseRecoveryRate":76.726,"requiredRevisionRateTo80":0.042671,"requiredRevisionRateTo100":0.303339,"requiredRevisionRateTo150yen":0.303352,"accountingBalanceLabel":"経常損益は判定不可 / 純利益","feeAdequacyLabel":"重点監視","revisionRiskScore":85,"revisionRiskLabel":"参考スコア80以上","diagnosisComment":"最新決算の経費回収率は76.7%であり、汚水処理費に対する使用料収入の不足割合が大きい状態です。費用や有収水量が変わらない仮定では、経費回収率100%相当の使用料収入は約30.3%の増加となる単純試算です。実際の使用料改定は、審議会、条例改正、一般会計繰入、投資計画等を踏まえて決まります。"}},{"surveyYear":2024,"fiscalYearLabel":"令和6年度","accountingType":"legal_applied","sewerFeeRevenue":48357,"householdFee20m3Yen":2530,"annualBillableVolume":419719,"wastewaterTreatmentCost":62951,"opexComponent":51423,"capitalCostComponent":11528,"operatingRevenue":48508,"operatingExpense":192668,"ordinaryRevenue":null,"ordinaryExpense":null,"ordinaryProfitLoss":8439,"netIncome":8439,"accumulatedDeficit":null,"totalRevenueNonLegal":null,"totalExpenseNonLegal":null,"realBalance":null,"revenueExpenditureRatio":null,"standardTransfer":null,"nonStandardTransfer":53861,"bondBalance":847627,"bondIssued":null,"bondRedemption":null,"servicePopulation":4794,"connectedPopulation":4655,"treatedVolume":482436,"dataQualityStatus":"ok","flagsJson":"[]","table40RainwaterBurden":0,"table40OtherAccountSubsidy":83702,"table40CapitalOtherAccountSubsidy":41373,"table40RainwaterBurdenNonStandard":0,"table40OtherAccountSubsidyNonStandard":16787,"table40CapitalOtherAccountSubsidyNonStandard":37074,"diagnosisResult":{"surveyYear":2024,"feeUnitPriceYenPerM3":115.2128,"treatmentCostYenPerM3":149.9837,"expenseRecoveryRate":76.8169,"requiredRevisionRateTo80":0.041437,"requiredRevisionRateTo100":0.301797,"requiredRevisionRateTo150yen":0.301939,"accountingBalanceLabel":"経常損益は判定不可 / 純利益","feeAdequacyLabel":"重点監視","revisionRiskScore":85,"revisionRiskLabel":"参考スコア80以上","diagnosisComment":"最新決算の経費回収率は76.8%であり、汚水処理費に対する使用料収入の不足割合が大きい状態です。費用や有収水量が変わらない仮定では、経費回収率100%相当の使用料収入は約30.2%の増加となる単純試算です。実際の使用料改定は、審議会、条例改正、一般会計繰入、投資計画等を踏まえて決まります。"}}]},{"businessKey":"17-1-000","businessName":"下水道事業（一） 事業コード1","businessType":"下水道事業（一） 事業コード1","estatBusinessCategory":"17/1/000","accountingType":"non_legal_applied","financialStory":{"year":"令和6年度","accountingType":"legal_applied","income":{"totalRevenue":211690,"totalExpense":203251,"operatingRevenue":48508,"nonOperatingRevenue":163175,"extraordinaryProfit":7,"operatingExpense":192668,"nonOperatingExpense":10576,"extraordinaryLoss":7,"netIncome":8439,"revenueBreakdown":[{"id":"sewer-fee","label":"下水道使用料","value":48357,"group":"operating","note":"使用者が支払う料金"},{"id":"rainwater-burden","label":"雨水処理負担金","value":0,"group":"operating","note":"公費で負担する雨水処理分"},{"id":"other-operating-revenue","label":"その他営業収益","value":151,"group":"operating"},{"id":"national-subsidy","label":"国庫補助金","value":5814,"group":"non-operating"},{"id":"prefectural-subsidy","label":"都道府県補助金","value":0,"group":"non-operating"},{"id":"other-account-subsidy","label":"他会計補助金（営業外収益）","value":83702,"group":"non-operating","note":"損益計算書上の科目。繰出基準内の補助も含むため、基準外繰入金とは一致しません"},{"id":"deferred-revenue-return","label":"長期前受金戻入","value":73623,"group":"non-operating","note":"過去の補助金等を減価償却に合わせて収益化した額"},{"id":"capital-cost-transfer","label":"資本費繰入収益","value":0,"group":"non-operating"},{"id":"miscellaneous-revenue","label":"雑収益","value":11,"group":"non-operating"},{"id":"extraordinary-profit-detail","label":"特別利益","value":7,"group":"extraordinary"}],"expenseBreakdown":[{"id":"pipeline","label":"管渠費","value":3360,"group":"operating"},{"id":"pump-station","label":"ポンプ場費","value":0,"group":"operating"},{"id":"treatment-plant","label":"処理場費","value":0,"group":"operating"},{"id":"outsourced-construction","label":"受託工事費","value":0,"group":"operating"},{"id":"business","label":"業務費","value":0,"group":"operating"},{"id":"administration","label":"総係費","value":25259,"group":"operating"},{"id":"depreciation","label":"減価償却費","value":141879,"group":"operating","note":"施設の価値を使用年数に配分した費用"},{"id":"asset-retirement","label":"資産減耗費","value":0,"group":"operating"},{"id":"regional-sewerage","label":"流域下水道管理運営費","value":22170,"group":"operating"},{"id":"other-operating-expense","label":"その他営業費用","value":0,"group":"operating"},{"id":"interest","label":"支払利息","value":8906,"group":"non-operating"},{"id":"other-non-operating-expense","label":"その他営業外費用","value":1670,"group":"non-operating"},{"id":"extraordinary-loss-detail","label":"特別損失","value":7,"group":"extraordinary"}]},"balance":{"fixedAssets":3055236,"currentAssets":37853,"deferredAssets":0,"totalAssets":3093089,"fixedLiabilities":745660,"currentLiabilities":115785,"deferredRevenue":1709513,"totalLiabilities":2570958,"capital":523138,"surplus":-1007,"capitalSurplus":0,"retainedEarnings":-1007,"otherSecuritiesValuationDifference":0,"totalNetAssets":522131,"priorNetAssets":513692,"priorCapital":523139,"priorSurplus":-9447,"priorCapitalSurplus":0,"priorRetainedEarnings":-9447,"priorOtherSecuritiesValuationDifference":0},"status":{"state":"ready","label":"必要項目取得済み","message":"金額は地方公営企業決算状況調査の原表値（千円）から構成しています。"},"trace":[{"id":"24-2024-20","label":"令和6年度 地方財政状況調査","table":"第20表 損益計算書","sourceUrl":"https://www.e-stat.go.jp/stat-search/file-download?&statInfId=000040327226&fileKind=0"},{"id":"25-2024-21","label":"令和6年度 地方財政状況調査","table":"第21表 費用構成表","sourceUrl":"https://www.e-stat.go.jp/stat-search/file-download?&statInfId=000040327228&fileKind=0"},{"id":"26-2024-22","label":"令和6年度 地方財政状況調査","table":"第22表 貸借対照表","sourceUrl":"https://www.e-stat.go.jp/stat-search/file-download?&statInfId=000040327230&fileKind=0"},{"id":"5-2023-22","label":"令和5年度 地方財政状況調査","table":"第22表 貸借対照表","sourceUrl":"https://www.e-stat.go.jp/stat-search/file-download?&statInfId=000040328395&fileKind=0","note":"前年度末の純資産と内訳の比較に使用"}]},"financialStatementsReady":true,"evidenceEntries":[["householdFee20m3Yen",{"value":2530,"unit":"yen_per_month_tax_included","tableNo":33,"tableName":"一般家庭用20m³／月使用料","sourceUrl":"https://www.e-stat.go.jp/stat-search/file-download?&statInfId=000032240286&fileKind=0"}],["sewerFeeRevenue",{"value":40665,"unit":"thousand_yen","tableNo":26,"tableName":"下水道使用料収入","sourceUrl":"https://www.e-stat.go.jp/stat-search/file-download?&statInfId=000032240283&fileKind=0"}],["annualBillableVolume",{"value":438448,"unit":"cubic_meter","tableNo":10,"tableName":"年間有収水量","sourceUrl":"https://www.e-stat.go.jp/stat-search/file-download?&statInfId=000032240270&fileKind=0"}],["wastewaterTreatmentCost",{"value":65767,"unit":"thousand_yen","tableNo":32,"tableName":"汚水処理費（合計）","sourceUrl":"https://www.e-stat.go.jp/stat-search/file-download?&statInfId=000032240285&fileKind=0"}],["opexComponent",{"value":35843,"unit":"thousand_yen","tableNo":32,"tableName":"汚水処理費（維持管理費分）","sourceUrl":"https://www.e-stat.go.jp/stat-search/file-download?&statInfId=000032240285&fileKind=0"}],["capitalCostComponent",{"value":29924,"unit":"thousand_yen","tableNo":32,"tableName":"汚水処理費（資本費分）","sourceUrl":"https://www.e-stat.go.jp/stat-search/file-download?&statInfId=000032240285&fileKind=0"}],["totalRevenueNonLegal",{"value":62275,"unit":"thousand_yen","tableNo":26,"tableName":"総収益","sourceUrl":"https://www.e-stat.go.jp/stat-search/file-download?&statInfId=000032240283&fileKind=0"}],["totalExpenseNonLegal",{"value":66048,"unit":"thousand_yen","tableNo":26,"tableName":"総費用","sourceUrl":"https://www.e-stat.go.jp/stat-search/file-download?&statInfId=000032240283&fileKind=0"}],["generalAccountTransfer",{"value":139899,"unit":"thousand_yen","tableNo":40,"tableName":"他会計繰入金","sourceUrl":"https://www.e-stat.go.jp/stat-search/file-download?&statInfId=000032240288&fileKind=0"}],["nonStandardTransfer",{"value":0,"unit":"thousand_yen","tableNo":40,"tableName":"基準外繰入合計","sourceUrl":"https://www.e-stat.go.jp/stat-search/file-download?&statInfId=000032240288&fileKind=0"}],["bondBalance",{"value":1184360,"unit":"thousand_yen","tableNo":24,"tableName":"地方債残高","sourceUrl":"https://www.e-stat.go.jp/stat-search/file-download?&statInfId=000032240281&fileKind=0"}],["servicePopulation",{"value":4966,"unit":"people","tableNo":10,"tableName":"現在処理区域内人口","sourceUrl":"https://www.e-stat.go.jp/stat-search/file-download?&statInfId=000032240270&fileKind=0"}],["connectedPopulation",{"value":4822,"unit":"people","tableNo":10,"tableName":"現在水洗便所設置済人口","sourceUrl":"https://www.e-stat.go.jp/stat-search/file-download?&statInfId=000032240270&fileKind=0"}],["treatedVolume",{"value":509823,"unit":"cubic_meter","tableNo":10,"tableName":"汚水処理水量","sourceUrl":"https://www.e-stat.go.jp/stat-search/file-download?&statInfId=000032240270&fileKind=0"}]],"annualFinancials":[{"surveyYear":2020,"fiscalYearLabel":"令和2年度","accountingType":"non_legal_applied","sewerFeeRevenue":55265,"householdFee20m3Yen":2530,"annualBillableVolume":443278,"wastewaterTreatmentCost":66492,"opexComponent":31734,"capitalCostComponent":34758,"operatingRevenue":null,"operatingExpense":null,"ordinaryRevenue":null,"ordinaryExpense":null,"ordinaryProfitLoss":null,"netIncome":null,"accumulatedDeficit":null,"totalRevenueNonLegal":97651,"totalExpenseNonLegal":75602,"realBalance":null,"revenueExpenditureRatio":129.1645723658104,"standardTransfer":null,"nonStandardTransfer":0,"bondBalance":1296149,"bondIssued":null,"bondRedemption":null,"servicePopulation":5015,"connectedPopulation":4870,"treatedVolume":521504,"dataQualityStatus":"ok","flagsJson":"[]","generalAccountTransfer":129767,"diagnosisResult":{"surveyYear":2020,"feeUnitPriceYenPerM3":124.6735,"treatmentCostYenPerM3":150.0007,"expenseRecoveryRate":83.1153,"requiredRevisionRateTo80":-0.037482,"requiredRevisionRateTo100":0.203148,"requiredRevisionRateTo150yen":0.203143,"accountingBalanceLabel":"実質収支は判定不可 / 収益的収支は均衡以上","feeAdequacyLabel":"要注意","revisionRiskScore":35,"revisionRiskLabel":"参考スコア30〜59","diagnosisComment":"最新決算の経費回収率は83.1%であり、下水道使用料収入が汚水処理費を下回っています。費用や有収水量が変わらない仮定では、経費回収率100%相当の使用料収入は約20.3%の増加となる単純試算です。"}},{"surveyYear":2021,"fiscalYearLabel":"令和3年度","accountingType":"non_legal_applied","sewerFeeRevenue":40665,"householdFee20m3Yen":2530,"annualBillableVolume":438448,"wastewaterTreatmentCost":65767,"opexComponent":35843,"capitalCostComponent":29924,"operatingRevenue":null,"operatingExpense":null,"ordinaryRevenue":null,"ordinaryExpense":null,"ordinaryProfitLoss":null,"netIncome":null,"accumulatedDeficit":null,"totalRevenueNonLegal":62275,"totalExpenseNonLegal":66048,"realBalance":null,"revenueExpenditureRatio":94.2874878875969,"standardTransfer":null,"nonStandardTransfer":0,"bondBalance":1184360,"bondIssued":null,"bondRedemption":null,"servicePopulation":4966,"connectedPopulation":4822,"treatedVolume":509823,"dataQualityStatus":"ok","flagsJson":"[]","generalAccountTransfer":139899,"diagnosisResult":{"surveyYear":2021,"feeUnitPriceYenPerM3":92.7476,"treatmentCostYenPerM3":149.9995,"expenseRecoveryRate":61.8319,"requiredRevisionRateTo80":0.293831,"requiredRevisionRateTo100":0.617288,"requiredRevisionRateTo150yen":0.617293,"accountingBalanceLabel":"実質収支は判定不可 / 収益的収支は不足","feeAdequacyLabel":"重点監視","revisionRiskScore":65,"revisionRiskLabel":"参考スコア60〜79","diagnosisComment":"最新決算の経費回収率は61.8%であり、汚水処理費に対する使用料収入の不足割合が大きい状態です。費用や有収水量が変わらない仮定では、経費回収率100%相当の使用料収入は約61.7%の増加となる単純試算です。実際の使用料改定は、審議会、条例改正、一般会計繰入、投資計画等を踏まえて決まります。"}}]},{"businessKey":"17-4-000","businessName":"下水道事業（一） 事業コード4","businessType":"下水道事業（一） 事業コード4","estatBusinessCategory":"17/4/000","accountingType":"legal_applied","financialStory":{"year":"令和6年度","accountingType":"legal_applied","income":{"totalRevenue":54832,"totalExpense":53661,"operatingRevenue":12805,"nonOperatingRevenue":42027,"extraordinaryProfit":0,"operatingExpense":50274,"nonOperatingExpense":3387,"extraordinaryLoss":0,"netIncome":1171,"revenueBreakdown":[{"id":"sewer-fee","label":"下水道使用料","value":12760,"group":"operating","note":"使用者が支払う料金"},{"id":"rainwater-burden","label":"雨水処理負担金","value":0,"group":"operating","note":"公費で負担する雨水処理分"},{"id":"other-operating-revenue","label":"その他営業収益","value":45,"group":"operating"},{"id":"national-subsidy","label":"国庫補助金","value":1736,"group":"non-operating"},{"id":"prefectural-subsidy","label":"都道府県補助金","value":0,"group":"non-operating"},{"id":"other-account-subsidy","label":"他会計補助金（営業外収益）","value":22615,"group":"non-operating","note":"損益計算書上の科目。繰出基準内の補助も含むため、基準外繰入金とは一致しません"},{"id":"deferred-revenue-return","label":"長期前受金戻入","value":17665,"group":"non-operating","note":"過去の補助金等を減価償却に合わせて収益化した額"},{"id":"capital-cost-transfer","label":"資本費繰入収益","value":0,"group":"non-operating"},{"id":"miscellaneous-revenue","label":"雑収益","value":3,"group":"non-operating"},{"id":"extraordinary-profit-detail","label":"特別利益","value":0,"group":"extraordinary"}],"expenseBreakdown":[{"id":"pipeline","label":"管渠費","value":1284,"group":"operating"},{"id":"pump-station","label":"ポンプ場費","value":0,"group":"operating"},{"id":"treatment-plant","label":"処理場費","value":0,"group":"operating"},{"id":"outsourced-construction","label":"受託工事費","value":0,"group":"operating"},{"id":"business","label":"業務費","value":0,"group":"operating"},{"id":"administration","label":"総係費","value":7565,"group":"operating"},{"id":"depreciation","label":"減価償却費","value":34803,"group":"operating","note":"施設の価値を使用年数に配分した費用"},{"id":"asset-retirement","label":"資産減耗費","value":0,"group":"operating"},{"id":"regional-sewerage","label":"流域下水道管理運営費","value":6622,"group":"operating"},{"id":"other-operating-expense","label":"その他営業費用","value":0,"group":"operating"},{"id":"interest","label":"支払利息","value":2888,"group":"non-operating"},{"id":"other-non-operating-expense","label":"その他営業外費用","value":499,"group":"non-operating"},{"id":"extraordinary-loss-detail","label":"特別損失","value":0,"group":"extraordinary"}]},"balance":{"fixedAssets":769778,"currentAssets":12139,"deferredAssets":0,"totalAssets":781917,"fixedLiabilities":260339,"currentLiabilities":45381,"deferredRevenue":453120,"totalLiabilities":758840,"capital":19966,"surplus":3111,"capitalSurplus":0,"retainedEarnings":3111,"otherSecuritiesValuationDifference":0,"totalNetAssets":23077,"priorNetAssets":21905,"priorCapital":19965,"priorSurplus":1940,"priorCapitalSurplus":0,"priorRetainedEarnings":1940,"priorOtherSecuritiesValuationDifference":0},"status":{"state":"ready","label":"必要項目取得済み","message":"金額は地方公営企業決算状況調査の原表値（千円）から構成しています。"},"trace":[{"id":"24-2024-20","label":"令和6年度 地方財政状況調査","table":"第20表 損益計算書","sourceUrl":"https://www.e-stat.go.jp/stat-search/file-download?&statInfId=000040327226&fileKind=0"},{"id":"25-2024-21","label":"令和6年度 地方財政状況調査","table":"第21表 費用構成表","sourceUrl":"https://www.e-stat.go.jp/stat-search/file-download?&statInfId=000040327228&fileKind=0"},{"id":"26-2024-22","label":"令和6年度 地方財政状況調査","table":"第22表 貸借対照表","sourceUrl":"https://www.e-stat.go.jp/stat-search/file-download?&statInfId=000040327230&fileKind=0"},{"id":"5-2023-22","label":"令和5年度 地方財政状況調査","table":"第22表 貸借対照表","sourceUrl":"https://www.e-stat.go.jp/stat-search/file-download?&statInfId=000040328395&fileKind=0","note":"前年度末の純資産と内訳の比較に使用"}]},"financialStatementsReady":true,"evidenceEntries":[["householdFee20m3Yen",{"value":2530,"unit":"yen_per_month_tax_included","tableNo":33,"tableName":"一般家庭用20m³／月使用料","sourceUrl":"https://www.e-stat.go.jp/stat-search/file-download?&statInfId=000040327245&fileKind=0"}],["sewerFeeRevenue",{"value":12760,"unit":"thousand_yen","tableNo":20,"tableName":"下水道使用料収入","sourceUrl":"https://www.e-stat.go.jp/stat-search/file-download?&statInfId=000040327226&fileKind=0"}],["annualBillableVolume",{"value":111596,"unit":"cubic_meter","tableNo":10,"tableName":"年間有収水量","sourceUrl":"https://www.e-stat.go.jp/stat-search/file-download?&statInfId=000040327218&fileKind=0"}],["wastewaterTreatmentCost",{"value":16739,"unit":"thousand_yen","tableNo":32,"tableName":"汚水処理費（合計）","sourceUrl":"https://www.e-stat.go.jp/stat-search/file-download?&statInfId=000040327244&fileKind=0"}],["opexComponent",{"value":15660,"unit":"thousand_yen","tableNo":32,"tableName":"汚水処理費（維持管理費分）","sourceUrl":"https://www.e-stat.go.jp/stat-search/file-download?&statInfId=000040327244&fileKind=0"}],["capitalCostComponent",{"value":1079,"unit":"thousand_yen","tableNo":32,"tableName":"汚水処理費（資本費分）","sourceUrl":"https://www.e-stat.go.jp/stat-search/file-download?&statInfId=000040327244&fileKind=0"}],["ordinaryProfitLoss",{"value":1171,"unit":"thousand_yen","tableNo":20,"tableName":"経常損益","sourceUrl":"https://www.e-stat.go.jp/stat-search/file-download?&statInfId=000040327226&fileKind=0"}],["netIncome",{"value":1171,"unit":"thousand_yen","tableNo":20,"tableName":"当年度純損益","sourceUrl":"https://www.e-stat.go.jp/stat-search/file-download?&statInfId=000040327226&fileKind=0"}],["generalAccountTransfer",{"value":22615,"unit":"thousand_yen","tableNo":40,"tableName":"他会計繰入金","sourceUrl":"https://www.e-stat.go.jp/stat-search/file-download?&statInfId=000040327247&fileKind=0"}],["nonStandardTransfer",{"value":24269,"unit":"thousand_yen","tableNo":40,"tableName":"基準外繰入合計","sourceUrl":"https://www.e-stat.go.jp/stat-search/file-download?&statInfId=000040327247&fileKind=0"}],["table40RainwaterBurden",{"value":0,"unit":"thousand_yen","tableNo":40,"tableName":"雨水処理負担金（実繰入額）","sourceUrl":"https://www.e-stat.go.jp/stat-search/file-download?&statInfId=000040327247&fileKind=0"}],["table40OtherAccountSubsidy",{"value":22615,"unit":"thousand_yen","tableNo":40,"tableName":"他会計補助金（実繰入額）","sourceUrl":"https://www.e-stat.go.jp/stat-search/file-download?&statInfId=000040327247&fileKind=0"}],["table40CapitalOtherAccountSubsidy",{"value":21766,"unit":"thousand_yen","tableNo":40,"tableName":"資本勘定の他会計補助金（実繰入額）","sourceUrl":"https://www.e-stat.go.jp/stat-search/file-download?&statInfId=000040327247&fileKind=0"}],["table40RainwaterBurdenNonStandard",{"value":0,"unit":"thousand_yen","tableNo":40,"tableName":"雨水処理負担金（基準外）","sourceUrl":"https://www.e-stat.go.jp/stat-search/file-download?&statInfId=000040327247&fileKind=0"}]],"annualFinancials":[{"surveyYear":2022,"fiscalYearLabel":"令和4年度","accountingType":"legal_applied","sewerFeeRevenue":12217,"householdFee20m3Yen":2530,"annualBillableVolume":106893,"wastewaterTreatmentCost":14793,"opexComponent":10005,"capitalCostComponent":4788,"operatingRevenue":12241,"operatingExpense":45176,"ordinaryRevenue":null,"ordinaryExpense":null,"ordinaryProfitLoss":1116,"netIncome":-125,"accumulatedDeficit":null,"totalRevenueNonLegal":null,"totalExpenseNonLegal":null,"realBalance":null,"revenueExpenditureRatio":null,"standardTransfer":null,"nonStandardTransfer":36012,"bondBalance":374554,"bondIssued":null,"bondRedemption":null,"servicePopulation":1478,"connectedPopulation":1435,"treatedVolume":124294,"dataQualityStatus":"ok","flagsJson":"[]","diagnosisResult":{"surveyYear":2022,"feeUnitPriceYenPerM3":114.2919,"treatmentCostYenPerM3":138.3907,"expenseRecoveryRate":82.5864,"requiredRevisionRateTo80":-0.031318,"requiredRevisionRateTo100":0.210853,"requiredRevisionRateTo150yen":0.312429,"accountingBalanceLabel":"経常損益は判定不可 / 純損失","feeAdequacyLabel":"要注意","revisionRiskScore":55,"revisionRiskLabel":"参考スコア30〜59","diagnosisComment":"最新決算の経費回収率は82.6%であり、下水道使用料収入が汚水処理費を下回っています。費用や有収水量が変わらない仮定では、経費回収率100%相当の使用料収入は約21.1%の増加となる単純試算です。"}},{"surveyYear":2023,"fiscalYearLabel":"令和5年度","accountingType":"legal_applied","sewerFeeRevenue":12735,"householdFee20m3Yen":2530,"annualBillableVolume":111459,"wastewaterTreatmentCost":16715,"opexComponent":10122,"capitalCostComponent":6593,"operatingRevenue":12758,"operatingExpense":45171,"ordinaryRevenue":null,"ordinaryExpense":null,"ordinaryProfitLoss":2069,"netIncome":2065,"accumulatedDeficit":null,"totalRevenueNonLegal":null,"totalExpenseNonLegal":null,"realBalance":null,"revenueExpenditureRatio":null,"standardTransfer":null,"nonStandardTransfer":28006,"bondBalance":336663,"bondIssued":null,"bondRedemption":null,"servicePopulation":1444,"connectedPopulation":1402,"treatedVolume":129603,"dataQualityStatus":"ok","flagsJson":"[]","diagnosisResult":{"surveyYear":2023,"feeUnitPriceYenPerM3":114.2573,"treatmentCostYenPerM3":149.9655,"expenseRecoveryRate":76.1891,"requiredRevisionRateTo80":0.050019,"requiredRevisionRateTo100":0.312524,"requiredRevisionRateTo150yen":0.312826,"accountingBalanceLabel":"経常損益は判定不可 / 純利益","feeAdequacyLabel":"重点監視","revisionRiskScore":85,"revisionRiskLabel":"参考スコア80以上","diagnosisComment":"最新決算の経費回収率は76.2%であり、汚水処理費に対する使用料収入の不足割合が大きい状態です。費用や有収水量が変わらない仮定では、経費回収率100%相当の使用料収入は約31.3%の増加となる単純試算です。実際の使用料改定は、審議会、条例改正、一般会計繰入、投資計画等を踏まえて決まります。"}},{"surveyYear":2024,"fiscalYearLabel":"令和6年度","accountingType":"legal_applied","sewerFeeRevenue":12760,"householdFee20m3Yen":2530,"annualBillableVolume":111596,"wastewaterTreatmentCost":16739,"opexComponent":15660,"capitalCostComponent":1079,"operatingRevenue":12805,"operatingExpense":50274,"ordinaryRevenue":null,"ordinaryExpense":null,"ordinaryProfitLoss":1171,"netIncome":1171,"accumulatedDeficit":null,"totalRevenueNonLegal":null,"totalExpenseNonLegal":null,"realBalance":null,"revenueExpenditureRatio":null,"standardTransfer":null,"nonStandardTransfer":24269,"bondBalance":301552,"bondIssued":null,"bondRedemption":null,"servicePopulation":1422,"connectedPopulation":1381,"treatedVolume":128271,"dataQualityStatus":"ok","flagsJson":"[]","table40RainwaterBurden":0,"table40OtherAccountSubsidy":22615,"table40CapitalOtherAccountSubsidy":21766,"table40RainwaterBurdenNonStandard":0,"table40OtherAccountSubsidyNonStandard":3299,"table40CapitalOtherAccountSubsidyNonStandard":20970,"diagnosisResult":{"surveyYear":2024,"feeUnitPriceYenPerM3":114.341,"treatmentCostYenPerM3":149.9964,"expenseRecoveryRate":76.2292,"requiredRevisionRateTo80":0.049467,"requiredRevisionRateTo100":0.311833,"requiredRevisionRateTo150yen":0.311865,"accountingBalanceLabel":"経常損益は判定不可 / 純利益","feeAdequacyLabel":"重点監視","revisionRiskScore":85,"revisionRiskLabel":"参考スコア80以上","diagnosisComment":"最新決算の経費回収率は76.2%であり、汚水処理費に対する使用料収入の不足割合が大きい状態です。費用や有収水量が変わらない仮定では、経費回収率100%相当の使用料収入は約31.2%の増加となる単純試算です。実際の使用料改定は、審議会、条例改正、一般会計繰入、投資計画等を踏まえて決まります。"}}]},{"businessKey":"17-4-000","businessName":"下水道事業（一） 事業コード4","businessType":"下水道事業（一） 事業コード4","estatBusinessCategory":"17/4/000","accountingType":"non_legal_applied","financialStory":{"year":"令和6年度","accountingType":"legal_applied","income":{"totalRevenue":54832,"totalExpense":53661,"operatingRevenue":12805,"nonOperatingRevenue":42027,"extraordinaryProfit":0,"operatingExpense":50274,"nonOperatingExpense":3387,"extraordinaryLoss":0,"netIncome":1171,"revenueBreakdown":[{"id":"sewer-fee","label":"下水道使用料","value":12760,"group":"operating","note":"使用者が支払う料金"},{"id":"rainwater-burden","label":"雨水処理負担金","value":0,"group":"operating","note":"公費で負担する雨水処理分"},{"id":"other-operating-revenue","label":"その他営業収益","value":45,"group":"operating"},{"id":"national-subsidy","label":"国庫補助金","value":1736,"group":"non-operating"},{"id":"prefectural-subsidy","label":"都道府県補助金","value":0,"group":"non-operating"},{"id":"other-account-subsidy","label":"他会計補助金（営業外収益）","value":22615,"group":"non-operating","note":"損益計算書上の科目。繰出基準内の補助も含むため、基準外繰入金とは一致しません"},{"id":"deferred-revenue-return","label":"長期前受金戻入","value":17665,"group":"non-operating","note":"過去の補助金等を減価償却に合わせて収益化した額"},{"id":"capital-cost-transfer","label":"資本費繰入収益","value":0,"group":"non-operating"},{"id":"miscellaneous-revenue","label":"雑収益","value":3,"group":"non-operating"},{"id":"extraordinary-profit-detail","label":"特別利益","value":0,"group":"extraordinary"}],"expenseBreakdown":[{"id":"pipeline","label":"管渠費","value":1284,"group":"operating"},{"id":"pump-station","label":"ポンプ場費","value":0,"group":"operating"},{"id":"treatment-plant","label":"処理場費","value":0,"group":"operating"},{"id":"outsourced-construction","label":"受託工事費","value":0,"group":"operating"},{"id":"business","label":"業務費","value":0,"group":"operating"},{"id":"administration","label":"総係費","value":7565,"group":"operating"},{"id":"depreciation","label":"減価償却費","value":34803,"group":"operating","note":"施設の価値を使用年数に配分した費用"},{"id":"asset-retirement","label":"資産減耗費","value":0,"group":"operating"},{"id":"regional-sewerage","label":"流域下水道管理運営費","value":6622,"group":"operating"},{"id":"other-operating-expense","label":"その他営業費用","value":0,"group":"operating"},{"id":"interest","label":"支払利息","value":2888,"group":"non-operating"},{"id":"other-non-operating-expense","label":"その他営業外費用","value":499,"group":"non-operating"},{"id":"extraordinary-loss-detail","label":"特別損失","value":0,"group":"extraordinary"}]},"balance":{"fixedAssets":769778,"currentAssets":12139,"deferredAssets":0,"totalAssets":781917,"fixedLiabilities":260339,"currentLiabilities":45381,"deferredRevenue":453120,"totalLiabilities":758840,"capital":19966,"surplus":3111,"capitalSurplus":0,"retainedEarnings":3111,"otherSecuritiesValuationDifference":0,"totalNetAssets":23077,"priorNetAssets":21905,"priorCapital":19965,"priorSurplus":1940,"priorCapitalSurplus":0,"priorRetainedEarnings":1940,"priorOtherSecuritiesValuationDifference":0},"status":{"state":"ready","label":"必要項目取得済み","message":"金額は地方公営企業決算状況調査の原表値（千円）から構成しています。"},"trace":[{"id":"24-2024-20","label":"令和6年度 地方財政状況調査","table":"第20表 損益計算書","sourceUrl":"https://www.e-stat.go.jp/stat-search/file-download?&statInfId=000040327226&fileKind=0"},{"id":"25-2024-21","label":"令和6年度 地方財政状況調査","table":"第21表 費用構成表","sourceUrl":"https://www.e-stat.go.jp/stat-search/file-download?&statInfId=000040327228&fileKind=0"},{"id":"26-2024-22","label":"令和6年度 地方財政状況調査","table":"第22表 貸借対照表","sourceUrl":"https://www.e-stat.go.jp/stat-search/file-download?&statInfId=000040327230&fileKind=0"},{"id":"5-2023-22","label":"令和5年度 地方財政状況調査","table":"第22表 貸借対照表","sourceUrl":"https://www.e-stat.go.jp/stat-search/file-download?&statInfId=000040328395&fileKind=0","note":"前年度末の純資産と内訳の比較に使用"}]},"financialStatementsReady":true,"evidenceEntries":[["householdFee20m3Yen",{"value":2530,"unit":"yen_per_month_tax_included","tableNo":33,"tableName":"一般家庭用20m³／月使用料","sourceUrl":"https://www.e-stat.go.jp/stat-search/file-download?&statInfId=000032240286&fileKind=0"}],["sewerFeeRevenue",{"value":12147,"unit":"thousand_yen","tableNo":26,"tableName":"下水道使用料収入","sourceUrl":"https://www.e-stat.go.jp/stat-search/file-download?&statInfId=000032240283&fileKind=0"}],["annualBillableVolume",{"value":119920,"unit":"cubic_meter","tableNo":10,"tableName":"年間有収水量","sourceUrl":"https://www.e-stat.go.jp/stat-search/file-download?&statInfId=000032240270&fileKind=0"}],["wastewaterTreatmentCost",{"value":17988,"unit":"thousand_yen","tableNo":32,"tableName":"汚水処理費（合計）","sourceUrl":"https://www.e-stat.go.jp/stat-search/file-download?&statInfId=000032240285&fileKind=0"}],["opexComponent",{"value":10707,"unit":"thousand_yen","tableNo":32,"tableName":"汚水処理費（維持管理費分）","sourceUrl":"https://www.e-stat.go.jp/stat-search/file-download?&statInfId=000032240285&fileKind=0"}],["capitalCostComponent",{"value":7281,"unit":"thousand_yen","tableNo":32,"tableName":"汚水処理費（資本費分）","sourceUrl":"https://www.e-stat.go.jp/stat-search/file-download?&statInfId=000032240285&fileKind=0"}],["totalRevenueNonLegal",{"value":19269,"unit":"thousand_yen","tableNo":26,"tableName":"総収益","sourceUrl":"https://www.e-stat.go.jp/stat-search/file-download?&statInfId=000032240283&fileKind=0"}],["totalExpenseNonLegal",{"value":20396,"unit":"thousand_yen","tableNo":26,"tableName":"総費用","sourceUrl":"https://www.e-stat.go.jp/stat-search/file-download?&statInfId=000032240283&fileKind=0"}],["generalAccountTransfer",{"value":49067,"unit":"thousand_yen","tableNo":40,"tableName":"他会計繰入金","sourceUrl":"https://www.e-stat.go.jp/stat-search/file-download?&statInfId=000032240288&fileKind=0"}],["nonStandardTransfer",{"value":0,"unit":"thousand_yen","tableNo":40,"tableName":"基準外繰入合計","sourceUrl":"https://www.e-stat.go.jp/stat-search/file-download?&statInfId=000032240288&fileKind=0"}],["bondBalance",{"value":418750,"unit":"thousand_yen","tableNo":24,"tableName":"地方債残高","sourceUrl":"https://www.e-stat.go.jp/stat-search/file-download?&statInfId=000032240281&fileKind=0"}],["servicePopulation",{"value":1529,"unit":"people","tableNo":10,"tableName":"現在処理区域内人口","sourceUrl":"https://www.e-stat.go.jp/stat-search/file-download?&statInfId=000032240270&fileKind=0"}],["connectedPopulation",{"value":1485,"unit":"people","tableNo":10,"tableName":"現在水洗便所設置済人口","sourceUrl":"https://www.e-stat.go.jp/stat-search/file-download?&statInfId=000032240270&fileKind=0"}],["treatedVolume",{"value":139442,"unit":"cubic_meter","tableNo":10,"tableName":"汚水処理水量","sourceUrl":"https://www.e-stat.go.jp/stat-search/file-download?&statInfId=000032240270&fileKind=0"}]],"annualFinancials":[{"surveyYear":2020,"fiscalYearLabel":"令和2年度","accountingType":"non_legal_applied","sewerFeeRevenue":16508,"householdFee20m3Yen":2530,"annualBillableVolume":123977,"wastewaterTreatmentCost":18597,"opexComponent":9480,"capitalCostComponent":9117,"operatingRevenue":null,"operatingExpense":null,"ordinaryRevenue":null,"ordinaryExpense":null,"ordinaryProfitLoss":null,"netIncome":null,"accumulatedDeficit":null,"totalRevenueNonLegal":30063,"totalExpenseNonLegal":23477,"realBalance":null,"revenueExpenditureRatio":128.0529880308387,"standardTransfer":null,"nonStandardTransfer":0,"bondBalance":462664,"bondIssued":null,"bondRedemption":null,"servicePopulation":1559,"connectedPopulation":1514,"treatedVolume":145855,"dataQualityStatus":"ok","flagsJson":"[]","generalAccountTransfer":49792,"diagnosisResult":{"surveyYear":2020,"feeUnitPriceYenPerM3":133.1537,"treatmentCostYenPerM3":150.0036,"expenseRecoveryRate":88.767,"requiredRevisionRateTo80":-0.098764,"requiredRevisionRateTo100":0.126545,"requiredRevisionRateTo150yen":0.126518,"accountingBalanceLabel":"実質収支は判定不可 / 収益的収支は均衡以上","feeAdequacyLabel":"要注意","revisionRiskScore":35,"revisionRiskLabel":"参考スコア30〜59","diagnosisComment":"最新決算の経費回収率は88.8%であり、下水道使用料収入が汚水処理費を下回っています。費用や有収水量が変わらない仮定では、経費回収率100%相当の使用料収入は約12.7%の増加となる単純試算です。"}},{"surveyYear":2021,"fiscalYearLabel":"令和3年度","accountingType":"non_legal_applied","sewerFeeRevenue":12147,"householdFee20m3Yen":2530,"annualBillableVolume":119920,"wastewaterTreatmentCost":17988,"opexComponent":10707,"capitalCostComponent":7281,"operatingRevenue":null,"operatingExpense":null,"ordinaryRevenue":null,"ordinaryExpense":null,"ordinaryProfitLoss":null,"netIncome":null,"accumulatedDeficit":null,"totalRevenueNonLegal":19269,"totalExpenseNonLegal":20396,"realBalance":null,"revenueExpenditureRatio":94.47440674642087,"standardTransfer":null,"nonStandardTransfer":0,"bondBalance":418750,"bondIssued":null,"bondRedemption":null,"servicePopulation":1529,"connectedPopulation":1485,"treatedVolume":139442,"dataQualityStatus":"ok","flagsJson":"[]","generalAccountTransfer":49067,"diagnosisResult":{"surveyYear":2021,"feeUnitPriceYenPerM3":101.2925,"treatmentCostYenPerM3":150,"expenseRecoveryRate":67.5284,"requiredRevisionRateTo80":0.184687,"requiredRevisionRateTo100":0.480858,"requiredRevisionRateTo150yen":0.48086,"accountingBalanceLabel":"実質収支は判定不可 / 収益的収支は不足","feeAdequacyLabel":"重点監視","revisionRiskScore":65,"revisionRiskLabel":"参考スコア60〜79","diagnosisComment":"最新決算の経費回収率は67.5%であり、汚水処理費に対する使用料収入の不足割合が大きい状態です。費用や有収水量が変わらない仮定では、経費回収率100%相当の使用料収入は約48.1%の増加となる単純試算です。実際の使用料改定は、審議会、条例改正、一般会計繰入、投資計画等を踏まえて決まります。"}}]}],"revisionEvents":[],"servedServiceMemberships":[]}